mudl/__init__.py
mudl/__main__.py
mudl/vk_auth.py
mudl/vk_downloader.py
mudl-0.1.5.dist-info/DESCRIPTION.rst
mudl-0.1.5.dist-info/METADATA
mudl-0.1.5.dist-info/RECORD
mudl-0.1.5.dist-info/WHEEL
mudl-0.1.5.dist-info/entry_points.txt
mudl-0.1.5.dist-info/metadata.json
mudl-0.1.5.dist-info/top_level.txt
