Metadata-Version: 2.0
Name: mudl
Version: 0.1.5
Summary: A cli tool for downloading music from VK in high quality
Home-page: https://github.com/yenbekbay/mudl
Author: Ayan Yenbekbay
Author-email: ayan.yenb@gmail.com
License: MIT
Keywords: music downloader mp3
Platform: UNKNOWN
Classifier: Environment :: Console
Classifier: License :: OSI Approved :: MIT License
Classifier: Programming Language :: Python :: 2.7
Classifier: Programming Language :: Python :: 2
Classifier: Programming Language :: Python :: 3.5
Classifier: Programming Language :: Python :: 3
Classifier: Topic :: Multimedia :: Sound/Audio
Requires-Dist: clint (>=0.3.4)
Requires-Dist: furl (>=0.4.8)
Requires-Dist: future (>=0.15.2)
Requires-Dist: musicbrainzngs (>=0.5)
Requires-Dist: mutagen (>=1.27)
Requires-Dist: soundcloud (>=0.4.1)
